loomanager/__init__.py
loomanager/__main__.py
loomanager/errors.py
loomanager/files.py
loomanager/input.py
loomanager/old__main__.py
loomanager/publish.py
loomanager-0.7.0.dist-info/METADATA
loomanager-0.7.0.dist-info/WHEEL
loomanager-0.7.0.dist-info/licenses/LICENSE
loomanager-0.7.0.dist-info/RECORD
